{
	"name": "copy_data_stg_dataset",
	"properties": {
		"activities": [
			{
				"name": "lookup_file_stg",
				"type": "Lookup",
				"dependsOn": [],
				"policy": {
					"timeout": "0.12:00:00",
					"retry": 0,
					"retryIntervalInSeconds": 30,
					"secureOutput": false,
					"secureInput": false
				},
				"userProperties": [],
				"typeProperties": {
					"source": {
						"type": "AzureSqlSource",
						"sqlReaderQuery": "select * from ess.adf_cpy_stg where active_flg =1",
						"queryTimeout": "02:00:00",
						"partitionOption": "None"
					},
					"dataset": {
						"referenceName": "File_mapping_src_stg",
						"type": "DatasetReference"
					},
					"firstRowOnly": false
				}
			},
			{
				"name": "Set variable1",
				"type": "SetVariable",
				"dependsOn": [
					{
						"activity": "lookup_file_stg",
						"dependencyConditions": [
							"Succeeded"
						]
					}
				],
				"policy": {
					"secureOutput": false,
					"secureInput": false
				},
				"userProperties": [],
				"typeProperties": {
					"variableName": "lookupOutput",
					"value": {
						"value": "@activity('lookup_file_stg').output.value",
						"type": "Expression"
					}
				}
			},
			{
				"name": "ForEach1",
				"type": "ForEach",
				"dependsOn": [
					{
						"activity": "Set variable1",
						"dependencyConditions": [
							"Succeeded"
						]
					}
				],
				"userProperties": [],
				"typeProperties": {
					"items": {
						"value": "@activity('lookup_file_stg').output.value",
						"type": "Expression"
					},
					"activities": [
						{
							"name": "Copy data1",
							"type": "Copy",
							"dependsOn": [],
							"policy": {
								"timeout": "0.12:00:00",
								"retry": 0,
								"retryIntervalInSeconds": 30,
								"secureOutput": false,
								"secureInput": false
							},
							"userProperties": [],
							"typeProperties": {
								"source": {
									"type": "DelimitedTextSource",
									"storeSettings": {
										"type": "AzureBlobFSReadSettings",
										"recursive": true,
										"wildcardFolderPath": {
											"value": "@item().path_src",
											"type": "Expression"
										},
										"wildcardFileName": {
											"value": "@item().filename_prefix_src",
											"type": "Expression"
										},
										"enablePartitionDiscovery": false
									},
									"formatSettings": {
										"type": "DelimitedTextReadSettings"
									}
								},
								"sink": {
									"type": "SqlServerSink",
									"writeBehavior": "insert",
									"sqlWriterUseTableLock": false
								},
								"enableStaging": false,
								"translator": {
									"type": "TabularTranslator",
									"typeConversion": true,
									"typeConversionSettings": {
										"allowDataTruncation": true,
										"treatBooleanAsNumber": false
									}
								}
							},
							"inputs": [
								{
									"referenceName": "SourceDataset",
									"type": "DatasetReference"
								}
							],
							"outputs": [
								{
									"referenceName": "Destination_ds",
									"type": "DatasetReference",
									"parameters": {
										"tablename": {
											"value": "@item().tablename_dest",
											"type": "Expression"
										}
									}
								}
							]
						}
					]
				}
			}
		],
		"variables": {
			"lookupOutput": {
				"type": "Array"
			}
		},
		"annotations": []
	}
}